README.txt
setup.py
sct/__init__.py
sct/__main__.py
sct/ecc.py
sct/keys.py
sct.egg-info/PKG-INFO
sct.egg-info/SOURCES.txt
sct.egg-info/dependency_links.txt
sct.egg-info/top_level.txt
sct.egg-info/zip-safe
test/test_ecc.py
test/test_keys.py