Metadata-Version: 1.0
Name: sct
Version: 0.1
Summary: sct package for crypto tools
Home-page: https://github.com/ShankarCodes
Author: shankar
Author-email: mailstoshankar@gmail.com
License: MIT
Platform: UNKNOWN
